sayori/__init__.py
sayori-1.0.6.dist-info/LICENSE.txt
sayori-1.0.6.dist-info/METADATA
sayori-1.0.6.dist-info/WHEEL
sayori-1.0.6.dist-info/top_level.txt
sayori-1.0.6.dist-info/RECORD
