Metadata-Version: 2.1
Name: sayori
Version: 1.0.6
Summary: Compose functions using pipeline notation.
Home-page: https://github.com/oruwmztbnz4q/sayori
Author: Tiffany
Author-email: oruwmztbnz4q@proton.me
Classifier: Programming Language :: Python :: 3
Classifier: Operating System :: OS Independent
Requires-Python: >=3.9
License-File: LICENSE.txt
